newslaunch/__init__.py
newslaunch/__main__.py
newslaunch/cli.py
newslaunch/guardian_api.py
newslaunch/kinesis_writer.py
newslaunch-0.0.1.dist-info/LICENSE
newslaunch-0.0.1.dist-info/METADATA
newslaunch-0.0.1.dist-info/WHEEL
newslaunch-0.0.1.dist-info/entry_points.txt
newslaunch-0.0.1.dist-info/top_level.txt
newslaunch-0.0.1.dist-info/RECORD
