Metadata-Version: 2.1
Name: newslaunch
Version: 0.0.1
Summary: A utility for retrieving and streaming news articles for analysis and processing.
Author: pavzari
License: Apache-2.0
Classifier: License :: OSI Approved :: Apache Software License
Requires-Python: >=3.8
License-File: LICENSE
Requires-Dist: click
Requires-Dist: requests
Requires-Dist: pydantic
Requires-Dist: boto3
Provides-Extra: test
Requires-Dist: pytest ; extra == 'test'
Requires-Dist: pytest-cov ; extra == 'test'
Requires-Dist: ruff ; extra == 'test'
Requires-Dist: black ; extra == 'test'
Requires-Dist: moto ; extra == 'test'
